quixplus/__ini__.py
quixplus/py.typed
quixplus/sources/__init__.py
quixplus/sources/csv.py
quixplus/sources/http.py
quixplus/sources/tornado_websocket.py
quixplus/sources/websocket.py
quixplus-25.0.1.dist-info/METADATA
quixplus-25.0.1.dist-info/WHEEL
quixplus-25.0.1.dist-info/licenses/LICENSE
quixplus-25.0.1.dist-info/RECORD
