Metadata-Version: 2.3
Name: quixplus
Version: 25.0.1
Summary: Custom sources and sinks for Quixstreams.
Author-email: Mac Anderson <mac@macanderson.com>
License: MIT
Requires-Python: >=3.11
Requires-Dist: aiohttp>=3.10.10
Requires-Dist: apscheduler>=3.10.4
Requires-Dist: cachetools>=5.5.0
Requires-Dist: clevercsv>=0.8.2
Requires-Dist: clickhouse-connect>=0.8.6
Requires-Dist: jsonpath-ng>=1.7.0
Requires-Dist: kafka-python-ng>=2.2.3
Requires-Dist: python-dotenv>=1.0.1
Requires-Dist: python-json-logger>=2.0.7
Requires-Dist: quixstreams>=3.1.1
Requires-Dist: tomllint>=0.3.0
Requires-Dist: tornado>=6.4.1
Requires-Dist: websocket-client>=1.8.0
